CHANGELOG.txt
LICENCE.txt
MANIFEST.in
README.txt
setup.py
base/Lib/site-packages/ghp_import.py
base/Lib/site-packages/six.py
base/Lib/site-packages/yaml_env_tag.py
base/Lib/site-packages/zipp.py
base/Lib/site-packages/Jinja2-3.1.2.dist-info/entry_points.txt
base/Lib/site-packages/Jinja2-3.1.2.dist-info/top_level.txt
base/Lib/site-packages/Markdown-3.4.1.dist-info/entry_points.txt
base/Lib/site-packages/Markdown-3.4.1.dist-info/top_level.txt
base/Lib/site-packages/MarkupSafe-2.1.1.dist-info/top_level.txt
base/Lib/site-packages/PyYAML-6.0.dist-info/top_level.txt
base/Lib/site-packages/Pygments-2.13.0.dist-info/entry_points.txt
base/Lib/site-packages/Pygments-2.13.0.dist-info/top_level.txt
base/Lib/site-packages/_distutils_hack/__init__.py
base/Lib/site-packages/_distutils_hack/override.py
base/Lib/site-packages/_yaml/__init__.py
base/Lib/site-packages/click/__init__.py
base/Lib/site-packages/click/_compat.py
base/Lib/site-packages/click/_termui_impl.py
base/Lib/site-packages/click/_textwrap.py
base/Lib/site-packages/click/_winconsole.py
base/Lib/site-packages/click/core.py
base/Lib/site-packages/click/decorators.py
base/Lib/site-packages/click/exceptions.py
base/Lib/site-packages/click/formatting.py
base/Lib/site-packages/click/globals.py
base/Lib/site-packages/click/parser.py
base/Lib/site-packages/click/shell_completion.py
base/Lib/site-packages/click/termui.py
base/Lib/site-packages/click/testing.py
base/Lib/site-packages/click/types.py
base/Lib/site-packages/click/utils.py
base/Lib/site-packages/click-8.1.3.dist-info/top_level.txt
base/Lib/site-packages/colorama/__init__.py
base/Lib/site-packages/colorama/ansi.py
base/Lib/site-packages/colorama/ansitowin32.py
base/Lib/site-packages/colorama/initialise.py
base/Lib/site-packages/colorama/win32.py
base/Lib/site-packages/colorama/winterm.py
base/Lib/site-packages/colorama-0.4.5.dist-info/LICENSE.txt
base/Lib/site-packages/colorama-0.4.5.dist-info/top_level.txt
base/Lib/site-packages/dateutil/__init__.py
base/Lib/site-packages/dateutil/_common.py
base/Lib/site-packages/dateutil/_version.py
base/Lib/site-packages/dateutil/easter.py
base/Lib/site-packages/dateutil/relativedelta.py
base/Lib/site-packages/dateutil/rrule.py
base/Lib/site-packages/dateutil/tzwin.py
base/Lib/site-packages/dateutil/utils.py
base/Lib/site-packages/dateutil/parser/__init__.py
base/Lib/site-packages/dateutil/parser/_parser.py
base/Lib/site-packages/dateutil/parser/isoparser.py
base/Lib/site-packages/dateutil/tz/__init__.py
base/Lib/site-packages/dateutil/tz/_common.py
base/Lib/site-packages/dateutil/tz/_factories.py
base/Lib/site-packages/dateutil/tz/tz.py
base/Lib/site-packages/dateutil/tz/win.py
base/Lib/site-packages/ghp_import-2.1.0.dist-info/entry_points.txt
base/Lib/site-packages/ghp_import-2.1.0.dist-info/top_level.txt
base/Lib/site-packages/griffe-0.22.2.dist-info/entry_points.txt
base/Lib/site-packages/importlib_metadata-5.0.0.dist-info/top_level.txt
base/Lib/site-packages/mergedeep-1.3.4.dist-info/top_level.txt
base/Lib/site-packages/mkdocs-1.3.0.dist-info/entry_points.txt
base/Lib/site-packages/mkdocs-1.3.0.dist-info/top_level.txt
base/Lib/site-packages/mkdocs_autorefs-0.4.1.dist-info/entry_points.txt
base/Lib/site-packages/mkdocs_material-8.3.8.dist-info/entry_points.txt
base/Lib/site-packages/mkdocs_material-8.3.8.dist-info/top_level.txt
base/Lib/site-packages/mkdocs_material_extensions-1.0.3.dist-info/top_level.txt
base/Lib/site-packages/mkdocstrings-0.19.0.dist-info/entry_points.txt
base/Lib/site-packages/packaging-21.3.dist-info/top_level.txt
base/Lib/site-packages/pip-22.2.2.dist-info/LICENSE.txt
base/Lib/site-packages/pip-22.2.2.dist-info/entry_points.txt
base/Lib/site-packages/pip-22.2.2.dist-info/top_level.txt
base/Lib/site-packages/python_dateutil-2.8.2.dist-info/top_level.txt
base/Lib/site-packages/setuptools-63.2.0.dist-info/entry_points.txt
base/Lib/site-packages/setuptools-63.2.0.dist-info/top_level.txt
base/Lib/site-packages/six-1.16.0.dist-info/top_level.txt
base/Lib/site-packages/watchdog-2.1.9.dist-info/entry_points.txt
base/Lib/site-packages/watchdog-2.1.9.dist-info/top_level.txt
base/Lib/site-packages/zipp-3.9.0.dist-info/top_level.txt
kamalbasiccalculator.egg-info/PKG-INFO
kamalbasiccalculator.egg-info/SOURCES.txt
kamalbasiccalculator.egg-info/dependency_links.txt
kamalbasiccalculator.egg-info/top_level.txt
