Metadata-Version: 2.1
Name: kamalbasiccalculator
Version: 0.0.2
Summary: A simple calculator with basic operations
Home-page: 
Author: Kamal K
Author-email: krajakk6@gmail.com
License: MIT
Keywords: calculator
Classifier: Programming Language :: Python :: 3
Classifier: License :: OSI Approved :: MIT License
Classifier: Operating System :: OS Independent
License-File: LICENCE.txt
